{
  "ID": "150122465",
  "Grade": "FRESHMAN",
  "AdvisorName": "Müjdat SOYTÜRK",
  "CourseRecords": [
    {
      "CourseCode": "ATA121",
      "LetterGrade": "BB",
      "Grade": 71.19829,
      "Season": "FALL",
      "RecordYear": "FRESHMAN",
      "Passed": true
    },
    {
      "CourseCode": "MBG1201",
      "LetterGrade": "FF",
      "Grade": 20.437416,
      "Season": "FALL",
      "RecordYear": "FRESHMAN",
      "Passed": false
    },
    {
      "CourseCode": "CSE1200",
      "LetterGrade": "FD",
      "Grade": 34.930733,
      "Season": "FALL",
      "RecordYear": "FRESHMAN",
      "Passed": false
    },
    {
      "CourseCode": "CSE1241",
      "LetterGrade": "AA",
      "Grade": 84.0025,
      "Season": "FALL",
      "RecordYear": "FRESHMAN",
      "Passed": true
    },
    {
      "CourseCode": "MATH1001",
      "LetterGrade": "BB",
      "Grade": 69.364876,
      "Season": "FALL",
      "RecordYear": "FRESHMAN",
      "Passed": true
    },
    {
      "CourseCode": "PHYS1101",
      "LetterGrade": "AA",
      "Grade": 94.70453,
      "Season": "FALL",
      "RecordYear": "FRESHMAN",
      "Passed": true
    },
    {
      "CourseCode": "PHYS1103",
      "LetterGrade": "CB",
      "Grade": 65.42186,
      "Season": "FALL",
      "RecordYear": "FRESHMAN",
      "Passed": true
    },
    {
      "CourseCode": "TRD121",
      "LetterGrade": "FF",
      "Grade": 32.134132,
      "Season": "FALL",
      "RecordYear": "FRESHMAN",
      "Passed": false
    }
  ],
  "FirstName": "Yasa",
  "MiddleName": null,
  "LastName": "GÖKTAS"
}