{
  "ID": "150118639",
  "Grade": "SENIOR",
  "AdvisorName": "Mustafa AĞAOĞLU",
  "CourseRecords": [
    {
      "CourseCode": "MBG1201",
      "LetterGrade": "DC",
      "Grade": 47.803963,
      "Season": "FALL",
      "RecordYear": "FRESHMAN",
      "Passed": true
    },
    {
      "CourseCode": "CSE1200",
      "LetterGrade": "BB",
      "Grade": 74.60055,
      "Season": "FALL",
      "RecordYear": "FRESHMAN",
      "Passed": true
    },
    {
      "CourseCode": "CSE1241",
      "LetterGrade": "AA",
      "Grade": 83.89119,
      "Season": "FALL",
      "RecordYear": "FRESHMAN",
      "Passed": true
    },
    {
      "CourseCode": "MATH1001",
      "LetterGrade": "DD",
      "Grade": 45.431488,
      "Season": "FALL",
      "RecordYear": "FRESHMAN",
      "Passed": true
    },
    {
      "CourseCode": "PHYS1101",
      "LetterGrade": "CC",
      "Grade": 57.79795,
      "Season": "FALL",
      "RecordYear": "FRESHMAN",
      "Passed": true
    },
    {
      "CourseCode": "PHYS1103",
      "LetterGrade": "AA",
      "Grade": 95.98381,
      "Season": "FALL",
      "RecordYear": "FRESHMAN",
      "Passed": true
    },
    {
      "CourseCode": "TRD121",
      "LetterGrade": "CB",
      "Grade": 64.50932,
      "Season": "FALL",
      "RecordYear": "FRESHMAN",
      "Passed": true
    },
    {
      "CourseCode": "ATA121",
      "LetterGrade": "DC",
      "Grade": 51.098846,
      "Season": "SPRING",
      "RecordYear": "FRESHMAN",
      "Passed": true
    },
    {
      "CourseCode": "ATA122",
      "LetterGrade": "CB",
      "Grade": 62.07287,
      "Season": "SPRING",
      "RecordYear": "FRESHMAN",
      "Passed": true
    },
    {
      "CourseCode": "CSE1242",
      "LetterGrade": "CC",
      "Grade": 59.864185,
      "Season": "SPRING",
      "RecordYear": "FRESHMAN",
      "Passed": true
    },
    {
      "CourseCode": "MATH1002",
      "LetterGrade": "FD",
      "Grade": 36.539783,
      "Season": "SPRING",
      "RecordYear": "FRESHMAN",
      "Passed": false
    },
    {
      "CourseCode": "PHYS1102",
      "LetterGrade": "AA",
      "Grade": 89.16523,
      "Season": "SPRING",
      "RecordYear": "FRESHMAN",
      "Passed": true
    },
    {
      "CourseCode": "PHYS1104",
      "LetterGrade": "BB",
      "Grade": 71.81569,
      "Season": "SPRING",
      "RecordYear": "FRESHMAN",
      "Passed": true
    },
    {
      "CourseCode": "TRD122",
      "LetterGrade": "DC",
      "Grade": 49.00824,
      "Season": "SPRING",
      "RecordYear": "FRESHMAN",
      "Passed": true
    },
    {
      "CourseCode": "NTE1004",
      "LetterGrade": "CC",
      "Grade": 54.885666,
      "Season": "SPRING",
      "RecordYear": "FRESHMAN",
      "Passed": true
    },
    {
      "CourseCode": "MATH1002",
      "LetterGrade": "AA",
      "Grade": 87.01512,
      "Season": "FALL",
      "RecordYear": "SOPHOMORE",
      "Passed": true
    },
    {
      "CourseCode": "MATH2256",
      "LetterGrade": "CB",
      "Grade": 62.708736,
      "Season": "FALL",
      "RecordYear": "SOPHOMORE",
      "Passed": true
    },
    {
      "CourseCode": "CSE2023",
      "LetterGrade": "AA",
      "Grade": 84.76482,
      "Season": "FALL",
      "RecordYear": "SOPHOMORE",
      "Passed": true
    },
    {
      "CourseCode": "CSE2225",
      "LetterGrade": "FF",
      "Grade": 20.215729,
      "Season": "FALL",
      "RecordYear": "SOPHOMORE",
      "Passed": false
    },
    {
      "CourseCode": "ECON2004",
      "LetterGrade": "BB",
      "Grade": 72.20815,
      "Season": "FALL",
      "RecordYear": "SOPHOMORE",
      "Passed": true
    },
    {
      "CourseCode": "MATH2055",
      "LetterGrade": "BB",
      "Grade": 67.73025,
      "Season": "FALL",
      "RecordYear": "SOPHOMORE",
      "Passed": true
    },
    {
      "CourseCode": "MATH2059",
      "LetterGrade": "CC",
      "Grade": 59.6292,
      "Season": "FALL",
      "RecordYear": "SOPHOMORE",
      "Passed": true
    },
    {
      "CourseCode": "CSE2225",
      "LetterGrade": "AA",
      "Grade": 90.886,
      "Season": "SPRING",
      "RecordYear": "SOPHOMORE",
      "Passed": true
    },
    {
      "CourseCode": "EE2031",
      "LetterGrade": "AA",
      "Grade": 93.221924,
      "Season": "SPRING",
      "RecordYear": "SOPHOMORE",
      "Passed": true
    },
    {
      "CourseCode": "CSE2138",
      "LetterGrade": "CC",
      "Grade": 58.481174,
      "Season": "SPRING",
      "RecordYear": "SOPHOMORE",
      "Passed": true
    },
    {
      "CourseCode": "CSE2260",
      "LetterGrade": "BA",
      "Grade": 75.438705,
      "Season": "SPRING",
      "RecordYear": "SOPHOMORE",
      "Passed": true
    },
    {
      "CourseCode": "STAT2253",
      "LetterGrade": "DC",
      "Grade": 47.99643,
      "Season": "SPRING",
      "RecordYear": "SOPHOMORE",
      "Passed": true
    },
    {
      "CourseCode": "CSE2246",
      "LetterGrade": "BB",
      "Grade": 74.60414,
      "Season": "FALL",
      "RecordYear": "JUNIOR",
      "Passed": true
    },
    {
      "CourseCode": "CSE3215",
      "LetterGrade": "AA",
      "Grade": 91.72555,
      "Season": "FALL",
      "RecordYear": "JUNIOR",
      "Passed": true
    },
    {
      "CourseCode": "CSE3033",
      "LetterGrade": "CC",
      "Grade": 55.458458,
      "Season": "FALL",
      "RecordYear": "JUNIOR",
      "Passed": true
    },
    {
      "CourseCode": "CSE3055",
      "LetterGrade": "DC",
      "Grade": 51.52939,
      "Season": "FALL",
      "RecordYear": "JUNIOR",
      "Passed": true
    },
    {
      "CourseCode": "CSE3063",
      "LetterGrade": "AA",
      "Grade": 97.00461,
      "Season": "FALL",
      "RecordYear": "JUNIOR",
      "Passed": true
    },
    {
      "CourseCode": "IE3081",
      "LetterGrade": "BA",
      "Grade": 78.71835,
      "Season": "FALL",
      "RecordYear": "JUNIOR",
      "Passed": true
    },
    {
      "CourseCode": "EE2032",
      "LetterGrade": "DC",
      "Grade": 51.45356,
      "Season": "SPRING",
      "RecordYear": "JUNIOR",
      "Passed": true
    },
    {
      "CourseCode": "CSE3038",
      "LetterGrade": "AA",
      "Grade": 86.63316,
      "Season": "SPRING",
      "RecordYear": "JUNIOR",
      "Passed": true
    },
    {
      "CourseCode": "CSE3044",
      "LetterGrade": "AA",
      "Grade": 89.013916,
      "Season": "SPRING",
      "RecordYear": "JUNIOR",
      "Passed": true
    },
    {
      "CourseCode": "CSE3048",
      "LetterGrade": "AA",
      "Grade": 97.282455,
      "Season": "SPRING",
      "RecordYear": "JUNIOR",
      "Passed": true
    },
    {
      "CourseCode": "CSE3264",
      "LetterGrade": "CC",
      "Grade": 52.891346,
      "Season": "SPRING",
      "RecordYear": "JUNIOR",
      "Passed": true
    },
    {
      "CourseCode": "IE3235",
      "LetterGrade": "BA",
      "Grade": 80.9411,
      "Season": "SPRING",
      "RecordYear": "JUNIOR",
      "Passed": true
    },
    {
      "CourseCode": "COM2202",
      "LetterGrade": "BB",
      "Grade": 70.715225,
      "Season": "SPRING",
      "RecordYear": "JUNIOR",
      "Passed": true
    },
    {
      "CourseCode": "CSE4074",
      "LetterGrade": "AA",
      "Grade": 83.58349,
      "Season": "FALL",
      "RecordYear": "SENIOR",
      "Passed": true
    },
    {
      "CourseCode": "CSE4219",
      "LetterGrade": "AA",
      "Grade": 84.76567,
      "Season": "FALL",
      "RecordYear": "SENIOR",
      "Passed": true
    },
    {
      "CourseCode": "CSE4297",
      "LetterGrade": "DD",
      "Grade": 45.697414,
      "Season": "FALL",
      "RecordYear": "SENIOR",
      "Passed": true
    },
    {
      "CourseCode": "ISG121",
      "LetterGrade": "BA",
      "Grade": 78.34436,
      "Season": "FALL",
      "RecordYear": "SENIOR",
      "Passed": true
    },
    {
      "CourseCode": "CSE4288",
      "LetterGrade": "AA",
      "Grade": 89.4011,
      "Season": "FALL",
      "RecordYear": "SENIOR",
      "Passed": true
    },
    {
      "CourseCode": "CSE4082",
      "LetterGrade": "DC",
      "Grade": 50.47989,
      "Season": "FALL",
      "RecordYear": "SENIOR",
      "Passed": true
    },
    {
      "CourseCode": "HSS3002",
      "LetterGrade": "BB",
      "Grade": 71.9083,
      "Season": "FALL",
      "RecordYear": "SENIOR",
      "Passed": true
    }
  ],
  "FirstName": "Zisan",
  "MiddleName": null,
  "LastName": "ORHAN"
}