{
  "ID": "150119785",
  "Grade": "SENIOR",
  "AdvisorName": "Betül Demiröz BOZ",
  "CourseRecords": [
    {
      "CourseCode": "ATA121",
      "LetterGrade": "AA",
      "Grade": 83.79938,
      "Season": "FALL",
      "RecordYear": "FRESHMAN",
      "Passed": true
    },
    {
      "CourseCode": "MBG1201",
      "LetterGrade": "CC",
      "Grade": 59.985054,
      "Season": "FALL",
      "RecordYear": "FRESHMAN",
      "Passed": true
    },
    {
      "CourseCode": "CSE1200",
      "LetterGrade": "BB",
      "Grade": 68.044495,
      "Season": "FALL",
      "RecordYear": "FRESHMAN",
      "Passed": true
    },
    {
      "CourseCode": "CSE1241",
      "LetterGrade": "FF",
      "Grade": 25.866558,
      "Season": "FALL",
      "RecordYear": "FRESHMAN",
      "Passed": false
    },
    {
      "CourseCode": "MATH1001",
      "LetterGrade": "AA",
      "Grade": 83.839455,
      "Season": "FALL",
      "RecordYear": "FRESHMAN",
      "Passed": true
    },
    {
      "CourseCode": "PHYS1101",
      "LetterGrade": "AA",
      "Grade": 97.41081,
      "Season": "FALL",
      "RecordYear": "FRESHMAN",
      "Passed": true
    },
    {
      "CourseCode": "PHYS1103",
      "LetterGrade": "AA",
      "Grade": 96.289185,
      "Season": "FALL",
      "RecordYear": "FRESHMAN",
      "Passed": true
    },
    {
      "CourseCode": "TRD121",
      "LetterGrade": "CC",
      "Grade": 55.611984,
      "Season": "FALL",
      "RecordYear": "FRESHMAN",
      "Passed": true
    },
    {
      "CourseCode": "CSE1241",
      "LetterGrade": "FF",
      "Grade": 24.27936,
      "Season": "SPRING",
      "RecordYear": "FRESHMAN",
      "Passed": false
    },
    {
      "CourseCode": "ATA122",
      "LetterGrade": "CB",
      "Grade": 61.677635,
      "Season": "SPRING",
      "RecordYear": "FRESHMAN",
      "Passed": true
    },
    {
      "CourseCode": "MATH1002",
      "LetterGrade": "CB",
      "Grade": 62.928864,
      "Season": "SPRING",
      "RecordYear": "FRESHMAN",
      "Passed": true
    },
    {
      "CourseCode": "MATH2256",
      "LetterGrade": "CC",
      "Grade": 59.775425,
      "Season": "SPRING",
      "RecordYear": "FRESHMAN",
      "Passed": true
    },
    {
      "CourseCode": "PHYS1102",
      "LetterGrade": "FD",
      "Grade": 39.477,
      "Season": "SPRING",
      "RecordYear": "FRESHMAN",
      "Passed": false
    },
    {
      "CourseCode": "PHYS1104",
      "LetterGrade": "DD",
      "Grade": 46.493164,
      "Season": "SPRING",
      "RecordYear": "FRESHMAN",
      "Passed": true
    },
    {
      "CourseCode": "TRD122",
      "LetterGrade": "FF",
      "Grade": 31.538939,
      "Season": "SPRING",
      "RecordYear": "FRESHMAN",
      "Passed": false
    },
    {
      "CourseCode": "NTE1008",
      "LetterGrade": "FF",
      "Grade": 25.694511,
      "Season": "SPRING",
      "RecordYear": "FRESHMAN",
      "Passed": false
    },
    {
      "CourseCode": "CSE1241",
      "LetterGrade": "AA",
      "Grade": 90.35586,
      "Season": "FALL",
      "RecordYear": "SOPHOMORE",
      "Passed": true
    },
    {
      "CourseCode": "PHYS1102",
      "LetterGrade": "DD",
      "Grade": 46.316994,
      "Season": "FALL",
      "RecordYear": "SOPHOMORE",
      "Passed": true
    },
    {
      "CourseCode": "TRD122",
      "LetterGrade": "CB",
      "Grade": 61.579525,
      "Season": "FALL",
      "RecordYear": "SOPHOMORE",
      "Passed": true
    },
    {
      "CourseCode": "NTE1008",
      "LetterGrade": "AA",
      "Grade": 93.806496,
      "Season": "FALL",
      "RecordYear": "SOPHOMORE",
      "Passed": true
    },
    {
      "CourseCode": "CSE2023",
      "LetterGrade": "BB",
      "Grade": 67.93129,
      "Season": "FALL",
      "RecordYear": "SOPHOMORE",
      "Passed": true
    },
    {
      "CourseCode": "ECON2004",
      "LetterGrade": "FF",
      "Grade": 19.534092,
      "Season": "FALL",
      "RecordYear": "SOPHOMORE",
      "Passed": false
    },
    {
      "CourseCode": "MATH2055",
      "LetterGrade": "CC",
      "Grade": 56.251854,
      "Season": "FALL",
      "RecordYear": "SOPHOMORE",
      "Passed": true
    },
    {
      "CourseCode": "MATH2059",
      "LetterGrade": "AA",
      "Grade": 85.83034,
      "Season": "FALL",
      "RecordYear": "SOPHOMORE",
      "Passed": true
    },
    {
      "CourseCode": "ECON2004",
      "LetterGrade": "AA",
      "Grade": 86.74896,
      "Season": "SPRING",
      "RecordYear": "SOPHOMORE",
      "Passed": true
    },
    {
      "CourseCode": "CSE1242",
      "LetterGrade": "FF",
      "Grade": 13.270335,
      "Season": "SPRING",
      "RecordYear": "SOPHOMORE",
      "Passed": false
    },
    {
      "CourseCode": "EE2031",
      "LetterGrade": "CB",
      "Grade": 64.82562,
      "Season": "SPRING",
      "RecordYear": "SOPHOMORE",
      "Passed": true
    },
    {
      "CourseCode": "CSE2138",
      "LetterGrade": "CC",
      "Grade": 59.247105,
      "Season": "SPRING",
      "RecordYear": "SOPHOMORE",
      "Passed": true
    },
    {
      "CourseCode": "STAT2253",
      "LetterGrade": "BA",
      "Grade": 82.09099,
      "Season": "SPRING",
      "RecordYear": "SOPHOMORE",
      "Passed": true
    },
    {
      "CourseCode": "CSE1242",
      "LetterGrade": "FD",
      "Grade": 35.341602,
      "Season": "FALL",
      "RecordYear": "JUNIOR",
      "Passed": false
    },
    {
      "CourseCode": "EE2032",
      "LetterGrade": "AA",
      "Grade": 97.8555,
      "Season": "FALL",
      "RecordYear": "JUNIOR",
      "Passed": true
    },
    {
      "CourseCode": "CSE3215",
      "LetterGrade": "FD",
      "Grade": 33.45692,
      "Season": "FALL",
      "RecordYear": "JUNIOR",
      "Passed": false
    },
    {
      "CourseCode": "IE3081",
      "LetterGrade": "FF",
      "Grade": 7.661819,
      "Season": "FALL",
      "RecordYear": "JUNIOR",
      "Passed": false
    },
    {
      "CourseCode": "CSE1242",
      "LetterGrade": "CB",
      "Grade": 61.85038,
      "Season": "SPRING",
      "RecordYear": "JUNIOR",
      "Passed": true
    },
    {
      "CourseCode": "CSE3215",
      "LetterGrade": "CB",
      "Grade": 67.41284,
      "Season": "SPRING",
      "RecordYear": "JUNIOR",
      "Passed": true
    },
    {
      "CourseCode": "IE3081",
      "LetterGrade": "DC",
      "Grade": 51.111366,
      "Season": "SPRING",
      "RecordYear": "JUNIOR",
      "Passed": true
    },
    {
      "CourseCode": "CSE3048",
      "LetterGrade": "FF",
      "Grade": 7.721855,
      "Season": "SPRING",
      "RecordYear": "JUNIOR",
      "Passed": false
    },
    {
      "CourseCode": "CSE3264",
      "LetterGrade": "BA",
      "Grade": 80.68891,
      "Season": "SPRING",
      "RecordYear": "JUNIOR",
      "Passed": true
    },
    {
      "CourseCode": "IE3235",
      "LetterGrade": "AA",
      "Grade": 98.71472,
      "Season": "SPRING",
      "RecordYear": "JUNIOR",
      "Passed": true
    },
    {
      "CourseCode": "COM2202",
      "LetterGrade": "AA",
      "Grade": 98.21963,
      "Season": "SPRING",
      "RecordYear": "JUNIOR",
      "Passed": true
    },
    {
      "CourseCode": "CSE3048",
      "LetterGrade": "DD",
      "Grade": 47.285454,
      "Season": "FALL",
      "RecordYear": "SENIOR",
      "Passed": true
    },
    {
      "CourseCode": "CSE2225",
      "LetterGrade": "FD",
      "Grade": 33.89211,
      "Season": "FALL",
      "RecordYear": "SENIOR",
      "Passed": false
    },
    {
      "CourseCode": "CSE2260",
      "LetterGrade": "AA",
      "Grade": 98.21881,
      "Season": "FALL",
      "RecordYear": "SENIOR",
      "Passed": true
    },
    {
      "CourseCode": "CSE3063",
      "LetterGrade": "BA",
      "Grade": 82.46647,
      "Season": "FALL",
      "RecordYear": "SENIOR",
      "Passed": true
    },
    {
      "CourseCode": "CSE4074",
      "LetterGrade": "CB",
      "Grade": 60.436977,
      "Season": "FALL",
      "RecordYear": "SENIOR",
      "Passed": true
    },
    {
      "CourseCode": "CSE4297",
      "LetterGrade": "DD",
      "Grade": 45.127014,
      "Season": "FALL",
      "RecordYear": "SENIOR",
      "Passed": true
    },
    {
      "CourseCode": "ISG121",
      "LetterGrade": "FF",
      "Grade": 10.722537,
      "Season": "FALL",
      "RecordYear": "SENIOR",
      "Passed": false
    },
    {
      "CourseCode": "CSE4288",
      "LetterGrade": "CB",
      "Grade": 67.38378,
      "Season": "FALL",
      "RecordYear": "SENIOR",
      "Passed": true
    },
    {
      "CourseCode": "CSE4061",
      "LetterGrade": "AA",
      "Grade": 87.19974,
      "Season": "FALL",
      "RecordYear": "SENIOR",
      "Passed": true
    },
    {
      "CourseCode": "COMM2060",
      "LetterGrade": "AA",
      "Grade": 91.29809,
      "Season": "FALL",
      "RecordYear": "SENIOR",
      "Passed": true
    }
  ],
  "FirstName": "Günsel",
  "MiddleName": null,
  "LastName": "YAVUZ"
}