{
  "ID": "150121517",
  "Grade": "SOPHOMORE",
  "AdvisorName": "Borahan TÜMER",
  "CourseRecords": [
    {
      "CourseCode": "ATA121",
      "LetterGrade": "AA",
      "Grade": 98.99347,
      "Season": "FALL",
      "RecordYear": "FRESHMAN",
      "Passed": true
    },
    {
      "CourseCode": "MBG1201",
      "LetterGrade": "AA",
      "Grade": 85.88722,
      "Season": "FALL",
      "RecordYear": "FRESHMAN",
      "Passed": true
    },
    {
      "CourseCode": "CSE1200",
      "LetterGrade": "AA",
      "Grade": 98.21533,
      "Season": "FALL",
      "RecordYear": "FRESHMAN",
      "Passed": true
    },
    {
      "CourseCode": "CSE1241",
      "LetterGrade": "AA",
      "Grade": 87.81665,
      "Season": "FALL",
      "RecordYear": "FRESHMAN",
      "Passed": true
    },
    {
      "CourseCode": "MATH1001",
      "LetterGrade": "AA",
      "Grade": 93.3532,
      "Season": "FALL",
      "RecordYear": "FRESHMAN",
      "Passed": true
    },
    {
      "CourseCode": "PHYS1101",
      "LetterGrade": "DC",
      "Grade": 52.056427,
      "Season": "FALL",
      "RecordYear": "FRESHMAN",
      "Passed": true
    },
    {
      "CourseCode": "PHYS1103",
      "LetterGrade": "AA",
      "Grade": 94.04816,
      "Season": "FALL",
      "RecordYear": "FRESHMAN",
      "Passed": true
    },
    {
      "CourseCode": "TRD121",
      "LetterGrade": "BA",
      "Grade": 75.474045,
      "Season": "FALL",
      "RecordYear": "FRESHMAN",
      "Passed": true
    },
    {
      "CourseCode": "ATA122",
      "LetterGrade": "CB",
      "Grade": 64.19911,
      "Season": "SPRING",
      "RecordYear": "FRESHMAN",
      "Passed": true
    },
    {
      "CourseCode": "CSE1242",
      "LetterGrade": "BA",
      "Grade": 76.93262,
      "Season": "SPRING",
      "RecordYear": "FRESHMAN",
      "Passed": true
    },
    {
      "CourseCode": "MATH1002",
      "LetterGrade": "AA",
      "Grade": 87.116066,
      "Season": "SPRING",
      "RecordYear": "FRESHMAN",
      "Passed": true
    },
    {
      "CourseCode": "MATH2256",
      "LetterGrade": "CC",
      "Grade": 56.11375,
      "Season": "SPRING",
      "RecordYear": "FRESHMAN",
      "Passed": true
    },
    {
      "CourseCode": "PHYS1102",
      "LetterGrade": "DC",
      "Grade": 50.891884,
      "Season": "SPRING",
      "RecordYear": "FRESHMAN",
      "Passed": true
    },
    {
      "CourseCode": "PHYS1104",
      "LetterGrade": "CB",
      "Grade": 63.691277,
      "Season": "SPRING",
      "RecordYear": "FRESHMAN",
      "Passed": true
    },
    {
      "CourseCode": "TRD122",
      "LetterGrade": "AA",
      "Grade": 92.151825,
      "Season": "SPRING",
      "RecordYear": "FRESHMAN",
      "Passed": true
    },
    {
      "CourseCode": "CAS1061",
      "LetterGrade": "BB",
      "Grade": 68.042046,
      "Season": "SPRING",
      "RecordYear": "FRESHMAN",
      "Passed": true
    },
    {
      "CourseCode": "CSE2023",
      "LetterGrade": "AA",
      "Grade": 98.855034,
      "Season": "FALL",
      "RecordYear": "SOPHOMORE",
      "Passed": true
    },
    {
      "CourseCode": "CSE2225",
      "LetterGrade": "FF",
      "Grade": 23.855917,
      "Season": "FALL",
      "RecordYear": "SOPHOMORE",
      "Passed": false
    },
    {
      "CourseCode": "EE2031",
      "LetterGrade": "DC",
      "Grade": 48.565514,
      "Season": "FALL",
      "RecordYear": "SOPHOMORE",
      "Passed": true
    },
    {
      "CourseCode": "MATH2055",
      "LetterGrade": "DC",
      "Grade": 50.63269,
      "Season": "FALL",
      "RecordYear": "SOPHOMORE",
      "Passed": true
    },
    {
      "CourseCode": "MATH2059",
      "LetterGrade": "FF",
      "Grade": 30.50997,
      "Season": "FALL",
      "RecordYear": "SOPHOMORE",
      "Passed": false
    }
  ],
  "FirstName": "Angi",
  "MiddleName": null,
  "LastName": "EZER"
}