{
  "ID": "150120398",
  "Grade": "JUNIOR",
  "AdvisorName": "Ömer KORÇAK",
  "CourseRecords": [
    {
      "CourseCode": "ATA121",
      "LetterGrade": "DC",
      "Grade": 50.026672,
      "Season": "FALL",
      "RecordYear": "FRESHMAN",
      "Passed": true
    },
    {
      "CourseCode": "MBG1201",
      "LetterGrade": "BB",
      "Grade": 68.89504,
      "Season": "FALL",
      "RecordYear": "FRESHMAN",
      "Passed": true
    },
    {
      "CourseCode": "CSE1200",
      "LetterGrade": "CB",
      "Grade": 65.012474,
      "Season": "FALL",
      "RecordYear": "FRESHMAN",
      "Passed": true
    },
    {
      "CourseCode": "CSE1241",
      "LetterGrade": "CB",
      "Grade": 64.859955,
      "Season": "FALL",
      "RecordYear": "FRESHMAN",
      "Passed": true
    },
    {
      "CourseCode": "MATH1001",
      "LetterGrade": "FF",
      "Grade": 20.101572,
      "Season": "FALL",
      "RecordYear": "FRESHMAN",
      "Passed": false
    },
    {
      "CourseCode": "PHYS1101",
      "LetterGrade": "BA",
      "Grade": 76.611694,
      "Season": "FALL",
      "RecordYear": "FRESHMAN",
      "Passed": true
    },
    {
      "CourseCode": "PHYS1103",
      "LetterGrade": "DD",
      "Grade": 45.860176,
      "Season": "FALL",
      "RecordYear": "FRESHMAN",
      "Passed": true
    },
    {
      "CourseCode": "TRD121",
      "LetterGrade": "CB",
      "Grade": 60.72946,
      "Season": "FALL",
      "RecordYear": "FRESHMAN",
      "Passed": true
    },
    {
      "CourseCode": "MATH1001",
      "LetterGrade": "FF",
      "Grade": 6.3682437,
      "Season": "SPRING",
      "RecordYear": "FRESHMAN",
      "Passed": false
    },
    {
      "CourseCode": "ATA122",
      "LetterGrade": "CC",
      "Grade": 57.341705,
      "Season": "SPRING",
      "RecordYear": "FRESHMAN",
      "Passed": true
    },
    {
      "CourseCode": "CSE1242",
      "LetterGrade": "AA",
      "Grade": 93.91785,
      "Season": "SPRING",
      "RecordYear": "FRESHMAN",
      "Passed": true
    },
    {
      "CourseCode": "MATH1002",
      "LetterGrade": "CC",
      "Grade": 57.443977,
      "Season": "SPRING",
      "RecordYear": "FRESHMAN",
      "Passed": true
    },
    {
      "CourseCode": "MATH2256",
      "LetterGrade": "CC",
      "Grade": 58.496704,
      "Season": "SPRING",
      "RecordYear": "FRESHMAN",
      "Passed": true
    },
    {
      "CourseCode": "PHYS1102",
      "LetterGrade": "DD",
      "Grade": 46.2103,
      "Season": "SPRING",
      "RecordYear": "FRESHMAN",
      "Passed": true
    },
    {
      "CourseCode": "PHYS1104",
      "LetterGrade": "BB",
      "Grade": 72.170876,
      "Season": "SPRING",
      "RecordYear": "FRESHMAN",
      "Passed": true
    },
    {
      "CourseCode": "TRD122",
      "LetterGrade": "FF",
      "Grade": 8.8023815,
      "Season": "SPRING",
      "RecordYear": "FRESHMAN",
      "Passed": false
    },
    {
      "CourseCode": "NTE1011",
      "LetterGrade": "AA",
      "Grade": 82.53165,
      "Season": "SPRING",
      "RecordYear": "FRESHMAN",
      "Passed": true
    },
    {
      "CourseCode": "MATH1001",
      "LetterGrade": "BB",
      "Grade": 70.3922,
      "Season": "FALL",
      "RecordYear": "SOPHOMORE",
      "Passed": true
    },
    {
      "CourseCode": "TRD122",
      "LetterGrade": "CB",
      "Grade": 61.551003,
      "Season": "FALL",
      "RecordYear": "SOPHOMORE",
      "Passed": true
    },
    {
      "CourseCode": "CSE2023",
      "LetterGrade": "DC",
      "Grade": 47.784378,
      "Season": "FALL",
      "RecordYear": "SOPHOMORE",
      "Passed": true
    },
    {
      "CourseCode": "CSE2225",
      "LetterGrade": "CC",
      "Grade": 56.353302,
      "Season": "FALL",
      "RecordYear": "SOPHOMORE",
      "Passed": true
    },
    {
      "CourseCode": "ECON2004",
      "LetterGrade": "CB",
      "Grade": 63.64798,
      "Season": "FALL",
      "RecordYear": "SOPHOMORE",
      "Passed": true
    },
    {
      "CourseCode": "EE2031",
      "LetterGrade": "CC",
      "Grade": 52.532738,
      "Season": "FALL",
      "RecordYear": "SOPHOMORE",
      "Passed": true
    },
    {
      "CourseCode": "MATH2055",
      "LetterGrade": "CC",
      "Grade": 58.45578,
      "Season": "FALL",
      "RecordYear": "SOPHOMORE",
      "Passed": true
    },
    {
      "CourseCode": "MATH2059",
      "LetterGrade": "BA",
      "Grade": 77.37555,
      "Season": "SPRING",
      "RecordYear": "SOPHOMORE",
      "Passed": true
    },
    {
      "CourseCode": "CSE2246",
      "LetterGrade": "AA",
      "Grade": 97.04465,
      "Season": "SPRING",
      "RecordYear": "SOPHOMORE",
      "Passed": true
    },
    {
      "CourseCode": "CSE2138",
      "LetterGrade": "CB",
      "Grade": 61.59838,
      "Season": "SPRING",
      "RecordYear": "SOPHOMORE",
      "Passed": true
    },
    {
      "CourseCode": "CSE2260",
      "LetterGrade": "BA",
      "Grade": 78.65141,
      "Season": "SPRING",
      "RecordYear": "SOPHOMORE",
      "Passed": true
    },
    {
      "CourseCode": "EE2032",
      "LetterGrade": "CB",
      "Grade": 67.38594,
      "Season": "SPRING",
      "RecordYear": "SOPHOMORE",
      "Passed": true
    },
    {
      "CourseCode": "STAT2253",
      "LetterGrade": "BB",
      "Grade": 71.42,
      "Season": "SPRING",
      "RecordYear": "SOPHOMORE",
      "Passed": true
    },
    {
      "CourseCode": "CSE3215",
      "LetterGrade": "BB",
      "Grade": 74.98906,
      "Season": "FALL",
      "RecordYear": "JUNIOR",
      "Passed": true
    },
    {
      "CourseCode": "CSE3033",
      "LetterGrade": "AA",
      "Grade": 91.205185,
      "Season": "FALL",
      "RecordYear": "JUNIOR",
      "Passed": true
    },
    {
      "CourseCode": "CSE3055",
      "LetterGrade": "AA",
      "Grade": 92.68472,
      "Season": "FALL",
      "RecordYear": "JUNIOR",
      "Passed": true
    },
    {
      "CourseCode": "CSE3063",
      "LetterGrade": "CB",
      "Grade": 64.75708,
      "Season": "FALL",
      "RecordYear": "JUNIOR",
      "Passed": true
    },
    {
      "CourseCode": "IE3081",
      "LetterGrade": "BA",
      "Grade": 79.023674,
      "Season": "FALL",
      "RecordYear": "JUNIOR",
      "Passed": true
    }
  ],
  "FirstName": "Isvendi",
  "MiddleName": null,
  "LastName": "ASLAN"
}