{
  "ID": "150118862",
  "Grade": "SENIOR",
  "AdvisorName": "Betül Demiröz BOZ",
  "CourseRecords": [
    {
      "CourseCode": "ATA121",
      "LetterGrade": "DC",
      "Grade": 52.266754,
      "Season": "FALL",
      "RecordYear": "FRESHMAN",
      "Passed": true
    },
    {
      "CourseCode": "MBG1201",
      "LetterGrade": "BA",
      "Grade": 81.879196,
      "Season": "FALL",
      "RecordYear": "FRESHMAN",
      "Passed": true
    },
    {
      "CourseCode": "CSE1200",
      "LetterGrade": "CC",
      "Grade": 53.60691,
      "Season": "FALL",
      "RecordYear": "FRESHMAN",
      "Passed": true
    },
    {
      "CourseCode": "CSE1241",
      "LetterGrade": "CB",
      "Grade": 61.918,
      "Season": "FALL",
      "RecordYear": "FRESHMAN",
      "Passed": true
    },
    {
      "CourseCode": "MATH1001",
      "LetterGrade": "AA",
      "Grade": 94.40684,
      "Season": "FALL",
      "RecordYear": "FRESHMAN",
      "Passed": true
    },
    {
      "CourseCode": "PHYS1101",
      "LetterGrade": "CC",
      "Grade": 53.1882,
      "Season": "FALL",
      "RecordYear": "FRESHMAN",
      "Passed": true
    },
    {
      "CourseCode": "PHYS1103",
      "LetterGrade": "AA",
      "Grade": 97.48317,
      "Season": "FALL",
      "RecordYear": "FRESHMAN",
      "Passed": true
    },
    {
      "CourseCode": "TRD121",
      "LetterGrade": "BA",
      "Grade": 76.51183,
      "Season": "FALL",
      "RecordYear": "FRESHMAN",
      "Passed": true
    },
    {
      "CourseCode": "ATA122",
      "LetterGrade": "CB",
      "Grade": 60.99898,
      "Season": "SPRING",
      "RecordYear": "FRESHMAN",
      "Passed": true
    },
    {
      "CourseCode": "CSE1242",
      "LetterGrade": "AA",
      "Grade": 82.66025,
      "Season": "SPRING",
      "RecordYear": "FRESHMAN",
      "Passed": true
    },
    {
      "CourseCode": "MATH1002",
      "LetterGrade": "BA",
      "Grade": 77.12805,
      "Season": "SPRING",
      "RecordYear": "FRESHMAN",
      "Passed": true
    },
    {
      "CourseCode": "MATH2256",
      "LetterGrade": "BA",
      "Grade": 81.73468,
      "Season": "SPRING",
      "RecordYear": "FRESHMAN",
      "Passed": true
    },
    {
      "CourseCode": "PHYS1102",
      "LetterGrade": "CB",
      "Grade": 67.097,
      "Season": "SPRING",
      "RecordYear": "FRESHMAN",
      "Passed": true
    },
    {
      "CourseCode": "PHYS1104",
      "LetterGrade": "CB",
      "Grade": 63.205563,
      "Season": "SPRING",
      "RecordYear": "FRESHMAN",
      "Passed": true
    },
    {
      "CourseCode": "TRD122",
      "LetterGrade": "BA",
      "Grade": 79.61423,
      "Season": "SPRING",
      "RecordYear": "FRESHMAN",
      "Passed": true
    },
    {
      "CourseCode": "COMM2060",
      "LetterGrade": "AA",
      "Grade": 89.397316,
      "Season": "SPRING",
      "RecordYear": "FRESHMAN",
      "Passed": true
    },
    {
      "CourseCode": "CSE2023",
      "LetterGrade": "AA",
      "Grade": 85.02867,
      "Season": "FALL",
      "RecordYear": "SOPHOMORE",
      "Passed": true
    },
    {
      "CourseCode": "CSE2225",
      "LetterGrade": "BB",
      "Grade": 73.84119,
      "Season": "FALL",
      "RecordYear": "SOPHOMORE",
      "Passed": true
    },
    {
      "CourseCode": "ECON2004",
      "LetterGrade": "FF",
      "Grade": 23.089233,
      "Season": "FALL",
      "RecordYear": "SOPHOMORE",
      "Passed": false
    },
    {
      "CourseCode": "EE2031",
      "LetterGrade": "CC",
      "Grade": 56.865795,
      "Season": "FALL",
      "RecordYear": "SOPHOMORE",
      "Passed": true
    },
    {
      "CourseCode": "MATH2055",
      "LetterGrade": "CB",
      "Grade": 62.722305,
      "Season": "FALL",
      "RecordYear": "SOPHOMORE",
      "Passed": true
    },
    {
      "CourseCode": "MATH2059",
      "LetterGrade": "CC",
      "Grade": 58.157715,
      "Season": "FALL",
      "RecordYear": "SOPHOMORE",
      "Passed": true
    },
    {
      "CourseCode": "ECON2004",
      "LetterGrade": "AA",
      "Grade": 89.87279,
      "Season": "SPRING",
      "RecordYear": "SOPHOMORE",
      "Passed": true
    },
    {
      "CourseCode": "CSE2246",
      "LetterGrade": "BB",
      "Grade": 73.32237,
      "Season": "SPRING",
      "RecordYear": "SOPHOMORE",
      "Passed": true
    },
    {
      "CourseCode": "CSE2138",
      "LetterGrade": "CC",
      "Grade": 52.734047,
      "Season": "SPRING",
      "RecordYear": "SOPHOMORE",
      "Passed": true
    },
    {
      "CourseCode": "CSE2260",
      "LetterGrade": "AA",
      "Grade": 90.96254,
      "Season": "SPRING",
      "RecordYear": "SOPHOMORE",
      "Passed": true
    },
    {
      "CourseCode": "EE2032",
      "LetterGrade": "CB",
      "Grade": 64.40906,
      "Season": "SPRING",
      "RecordYear": "SOPHOMORE",
      "Passed": true
    },
    {
      "CourseCode": "STAT2253",
      "LetterGrade": "CB",
      "Grade": 62.276104,
      "Season": "SPRING",
      "RecordYear": "SOPHOMORE",
      "Passed": true
    },
    {
      "CourseCode": "CSE3215",
      "LetterGrade": "AA",
      "Grade": 90.20826,
      "Season": "FALL",
      "RecordYear": "JUNIOR",
      "Passed": true
    },
    {
      "CourseCode": "CSE3033",
      "LetterGrade": "AA",
      "Grade": 84.85251,
      "Season": "FALL",
      "RecordYear": "JUNIOR",
      "Passed": true
    },
    {
      "CourseCode": "CSE3055",
      "LetterGrade": "BB",
      "Grade": 70.823044,
      "Season": "FALL",
      "RecordYear": "JUNIOR",
      "Passed": true
    },
    {
      "CourseCode": "CSE3063",
      "LetterGrade": "CB",
      "Grade": 62.483437,
      "Season": "FALL",
      "RecordYear": "JUNIOR",
      "Passed": true
    },
    {
      "CourseCode": "IE3081",
      "LetterGrade": "BB",
      "Grade": 70.829056,
      "Season": "FALL",
      "RecordYear": "JUNIOR",
      "Passed": true
    },
    {
      "CourseCode": "CSE3038",
      "LetterGrade": "DD",
      "Grade": 46.265335,
      "Season": "SPRING",
      "RecordYear": "JUNIOR",
      "Passed": true
    },
    {
      "CourseCode": "CSE3044",
      "LetterGrade": "CB",
      "Grade": 63.009594,
      "Season": "SPRING",
      "RecordYear": "JUNIOR",
      "Passed": true
    },
    {
      "CourseCode": "CSE3048",
      "LetterGrade": "AA",
      "Grade": 84.6812,
      "Season": "SPRING",
      "RecordYear": "JUNIOR",
      "Passed": true
    },
    {
      "CourseCode": "CSE3264",
      "LetterGrade": "DC",
      "Grade": 51.284733,
      "Season": "SPRING",
      "RecordYear": "JUNIOR",
      "Passed": true
    },
    {
      "CourseCode": "IE3235",
      "LetterGrade": "CB",
      "Grade": 62.142082,
      "Season": "SPRING",
      "RecordYear": "JUNIOR",
      "Passed": true
    },
    {
      "CourseCode": "COM2202",
      "LetterGrade": "AA",
      "Grade": 95.48843,
      "Season": "SPRING",
      "RecordYear": "JUNIOR",
      "Passed": true
    },
    {
      "CourseCode": "CSE4074",
      "LetterGrade": "AA",
      "Grade": 92.48425,
      "Season": "FALL",
      "RecordYear": "SENIOR",
      "Passed": true
    },
    {
      "CourseCode": "CSE4219",
      "LetterGrade": "FF",
      "Grade": 17.783276,
      "Season": "FALL",
      "RecordYear": "SENIOR",
      "Passed": false
    },
    {
      "CourseCode": "CSE4297",
      "LetterGrade": "AA",
      "Grade": 83.373146,
      "Season": "FALL",
      "RecordYear": "SENIOR",
      "Passed": true
    },
    {
      "CourseCode": "ISG121",
      "LetterGrade": "CC",
      "Grade": 54.92191,
      "Season": "FALL",
      "RecordYear": "SENIOR",
      "Passed": true
    },
    {
      "CourseCode": "CSE4288",
      "LetterGrade": "BA",
      "Grade": 81.314064,
      "Season": "FALL",
      "RecordYear": "SENIOR",
      "Passed": true
    },
    {
      "CourseCode": "CSE4086",
      "LetterGrade": "DD",
      "Grade": 47.388035,
      "Season": "FALL",
      "RecordYear": "SENIOR",
      "Passed": true
    },
    {
      "CourseCode": "NTE1014",
      "LetterGrade": "AA",
      "Grade": 99.755585,
      "Season": "FALL",
      "RecordYear": "SENIOR",
      "Passed": true
    }
  ],
  "FirstName": "Günerkan",
  "MiddleName": "Sebüktekin",
  "LastName": "GÖKSEL"
}